Numerical-Computers-Exercises/Verilog/Task_1/ex2.v
module NAND(A,B,S);
    input A,B;
    output S;
    
    assign S = ~(A & B);
endmodule

module st_fa(A, B, Ci, Co, S);
    input wire A, B, Ci;
    output wire S, Co;

    wire w1, w2, w3,w4,w5,w6,w7,w8,w9;
    
    NAND n1(A, B, w1);
    NAND n2(w1, A, w2);
    NAND n3(w1, B, w3);
    NAND n4(w2, w3, w4); 

    NAND n5(w4, Ci, w5);
    NAND n6(w5, w4, w6);
    NAND n7(w5, Ci, w7);
    NAND n8(w6, w7, S);  

    
    NAND n9(A, B, w8);
    NAND n10(w4, Ci, w9);
    NAND n11(w8, w9, Co);  

endmodule

module st_fa_tb();
    reg A, B, Ci;
    wire S, Co;
    
    st_fa uut(A, B, Ci, S, Co);

    initial begin
        $dumpfile("ex2.vcd"); 
        $dumpvars(0, st_fa_tb); 

        $monitor("Time=%0t A=%b B=%b Ci=%b -> S=%b Cout=%b", $time, A, B, Ci, S, Co);
        A = 0; B = 0; Ci = 0;
        #10 A = 0; B = 0; Ci = 1;
        #10 A = 0; B = 1; Ci = 0;
        #10 A = 0; B = 1; Ci = 1;
        #10 A = 1; B = 0; Ci = 0;
        #10 A = 1; B = 0; Ci = 1;
        #10 A = 1; B = 1; Ci = 0;
        #10 A = 1; B = 1; Ci = 1;
        #10 $finish;
    end
endmodule

Numerical-Computers-Exercises/Verilog/Task_1/ex2.vcd
$date
	Thu Mar 20 09:18:11 2025
$end
$version
	Icarus Verilog
$end
$timescale
	1s
$end
$scope module st_fa_tb $end
$var wire 1 ! S $end
$var wire 1 " Co $end
$var reg 1 # A $end
$var reg 1 $ B $end
$var reg 1 % Ci $end
$scope module uut $end
$var wire 1 # A $end
$var wire 1 $ B $end
$var wire 1 % Ci $end
$var wire 1 & w9 $end
$var wire 1 ' w8 $end
$var wire 1 ( w7 $end
$var wire 1 ) w6 $end
$var wire 1 * w5 $end
$var wire 1 + w4 $end
$var wire 1 , w3 $end
$var wire 1 - w2 $end
$var wire 1 . w1 $end
$var wire 1 " S $end
$var wire 1 ! Co $end
$scope module n1 $end
$var wire 1 # A $end
$var wire 1 $ B $end
$var wire 1 . S $end
$upscope $end
$scope module n10 $end
$var wire 1 % B $end
$var wire 1 & S $end
$var wire 1 + A $end
$upscope $end
$scope module n11 $end
$var wire 1 & B $end
$var wire 1 ! S $end
$var wire 1 ' A $end
$upscope $end
$scope module n2 $end
$var wire 1 . A $end
$var wire 1 # B $end
$var wire 1 - S $end
$upscope $end
$scope module n3 $end
$var wire 1 . A $end
$var wire 1 $ B $end
$var wire 1 , S $end
$upscope $end
$scope module n4 $end
$var wire 1 - A $end
$var wire 1 , B $end
$var wire 1 + S $end
$upscope $end
$scope module n5 $end
$var wire 1 + A $end
$var wire 1 % B $end
$var wire 1 * S $end
$upscope $end
$scope module n6 $end
$var wire 1 * A $end
$var wire 1 + B $end
$var wire 1 ) S $end
$upscope $end
$scope module n7 $end
$var wire 1 * A $end
$var wire 1 % B $end
$var wire 1 ( S $end
$upscope $end
$scope module n8 $end
$var wire 1 ) A $end
$var wire 1 ( B $end
$var wire 1 " S $end
$upscope $end
$scope module n9 $end
$var wire 1 # A $end
$var wire 1 $ B $end
$var wire 1 ' S $end
$upscope $end
$upscope $end
$upscope $end
$enddefinitions $end
$comment Show the parameter values. $end
$dumpall
$end
#0
$dumpvars
1.
1-
1,
0+
1*
1)
1(
1'
1&
0%
0$
0#
0"
0!
$end
#10
1"
0(
1%
#20
0)
1"
1+
1(
0,
0%
1$
#30
0"
1!
1)
0&
0*
1(
1%
#40
1"
0!
0)
1&
1*
1,
0-
0%
0$
1#
#50
0"
1!
1)
0&
0*
1(
1%
#60
0"
0+
1)
1-
1&
1*
0.
1,
0'
0%
1$
#70
1"
0(
1%
