Numerical-Computers-Exercises/Verilog/Task_3/ex1.v
module nor_gate(out, A, B);
    input A, B;
    output out;
    
    supply1 pwr;
    supply0 gnd;
    
    wire out_int;
    
    pmos(out_int, pwr, A);
    pmos(out, out_int, B);
    
    nmos(out, gnd, A);
    nmos(out, gnd, B);
endmodule


module mux_2to1(out, i0, i1, s);
    input i0, i1, s;
    output out;
    wire sbar;
    wire w0, w1;
  
    supply1 vdd;
    supply0 gnd;
    
    nmos(sbar, gnd, s);
    pmos(sbar, vdd, s);
    

    nand n0(w0, i0, sbar);
    nand n1(w1, i1, s);
    nand n2(out, w0, w1);
endmodule

module tb();
    reg i0, i1, s;
    wire out;

    mux_2to1 m1(out, i0, i1, s);

    initial begin
        $dumpfile("ex1.vcd");
        $dumpvars(0, tb);

        i0=0; i1=0; s=0;
        #10 i0=0; i1=1; s=0;
        #10 i0=1; i1=0; s=0;
        #10 i0=1; i1=1; s=0;
        #10 i0=0; i1=0; s=1;
        #10 i0=0; i1=1; s=1;
        #10 i0=1; i1=0; s=1;
        #10 i0=1; i1=1; s=1;
        #10 $finish;
    end

    initial $monitor("%b, %b, %b, %b", i0, i1, s, out);
endmodule

Numerical-Computers-Exercises/Verilog/Task_3/ex1.vcd
$date
	Thu Apr 03 09:20:13 2025
$end
$version
	Icarus Verilog
$end
$timescale
	1s
$end
$scope module tb $end
$var wire 1 ! out $end
$var reg 1 " i0 $end
$var reg 1 # i1 $end
$var reg 1 $ s $end
$scope module m1 $end
$var wire 1 % gnd $end
$var wire 1 " i0 $end
$var wire 1 # i1 $end
$var wire 1 ! out $end
$var wire 1 $ s $end
$var wire 1 & sbar $end
$var wire 1 ' vdd $end
$var wire 1 ( w0 $end
$var wire 1 ) w1 $end
$upscope $end
$upscope $end
$enddefinitions $end
$comment Show the parameter values. $end
$dumpall
$end
#0
$dumpvars
1)
1(
1'
1&
0%
0$
0#
0"
0!
$end
#10
1#
#20
1!
0(
0#
1"
#30
1#
#40
0!
1(
0&
1$
0#
0"
#50
1!
0)
1#
#60
0!
1)
0#
1"
#70
1!
0)
1#
